jupytergis_mcp/__init__.py
jupytergis_mcp/server.py
jupytergis_mcp-0.1.0rc1.dist-info/WHEEL
jupytergis_mcp-0.1.0rc1.dist-info/entry_points.txt
jupytergis_mcp-0.1.0rc1.dist-info/METADATA
jupytergis_mcp-0.1.0rc1.dist-info/RECORD
