Metadata-Version: 2.4
Name: jupytergis-mcp
Version: 0.1.0rc1
Summary: An MCP server for JupyterGIS that allows you to control it using LLMs/natural language.
Keywords: jupytergis,jupyterlab,mcp,geospatial,gis
Author: asmith26
License-Expression: Apache-2.0
Classifier: Programming Language :: Python :: 3
Classifier: Programming Language :: Python :: 3.10
Classifier: Programming Language :: Python :: 3.11
Classifier: Programming Language :: Python :: 3.12
Classifier: Programming Language :: Python :: 3.13
Classifier: Programming Language :: Python :: 3.14
Requires-Dist: fastmcp>=2.12.5
Requires-Dist: jupytergis>=0.9.2
Requires-Dist: mlflow>=3.2.0 ; extra == 'examples'
Requires-Dist: openai-agents[litellm]>=0.2.11 ; extra == 'examples'
Requires-Python: >=3.10
Project-URL: Homepage, https://github.com/asmith26/jupytergis-mcp
Provides-Extra: examples
